Thedex_Messaging/Thedex.py
Thedex_Messaging/__init__.py
ThedexMessaging-0.1.4.dist-info/LICENSE
ThedexMessaging-0.1.4.dist-info/METADATA
ThedexMessaging-0.1.4.dist-info/WHEEL
ThedexMessaging-0.1.4.dist-info/top_level.txt
ThedexMessaging-0.1.4.dist-info/RECORD
