Metadata-Version: 2.1
Name: ThedexMessaging
Version: 0.1.4
Summary: A Package to create Messages for the Thedex Messaging API
Home-page: https://github.com/KaiReichart/Thedex_Messaging.py
Author: Kai Reichart
Author-email: kai@reichart.dev
License: UNKNOWN
Download-URL: https://github.com/KaiReichart/Thedex_Messaging.py/archive/v0.1.4.tar.gz
Platform: UNKNOWN
Classifier: Development Status :: 4 - Beta
Classifier: Programming Language :: Python :: 3
Classifier: License :: OSI Approved :: MIT License
Classifier: Operating System :: OS Independent
Requires-Python: >=3.6
Requires-Dist: datetime
